CnbcNews/__init__.py
CnbcNews/main.py
CnbcNews-5.7.dist-info/METADATA
CnbcNews-5.7.dist-info/WHEEL
CnbcNews-5.7.dist-info/entry_points.txt
CnbcNews-5.7.dist-info/top_level.txt
CnbcNews-5.7.dist-info/RECORD
