Metadata-Version: 2.1
Name: CnbcNews
Version: 5.7
Requires-Dist: requests
Requires-Dist: beautifulsoup4
Requires-Dist: pandas
